pickalotto.py
setup.py
PickALotto.egg-info/PKG-INFO
PickALotto.egg-info/SOURCES.txt
PickALotto.egg-info/dependency_links.txt
PickALotto.egg-info/entry_points.txt
PickALotto.egg-info/not-zip-safe
PickALotto.egg-info/requires.txt
PickALotto.egg-info/top_level.txt